{
  "0": {
    "extras": [],
    "offense": "Brooms Up",
    "defense": "",
    "length": -1,
    "time": "0000",
    "result": "BU",
    "primary": [
      "TEXAS-DAVIS ROE"
    ],
    "secondary": [
      "TEXAS-RICHMOND KEELING"
    ],
    "period": "FLOOR"
  },
  "1": {
    "extras": [],
    "offense": "TEXAS",
    "defense": "SHSU",
    "time": "0048",
    "result": "ED",
    "primary": [
      "TEXAS-CAROLINE TAO"
    ],
    "secondary": [],
    "period": "FLOOR",
    "length": 48
  },
  "2": {
    "extras": [],
    "offense": "SHSU",
    "defense": "TEXAS",
    "time": "0110",
    "result": "GP",
    "primary": [
      "SHSU-HALEY DUPRE"
    ],
    "secondary": [
      "SHSU-HAYDEN BOYES"
    ],
    "period": "FLOOR",
    "length": 62
  },
  "3": {
    "extras": [],
    "offense": "TEXAS",
    "defense": "SHSU",
    "time": "0220",
    "result": "EP",
    "primary": [
      "TEXAS-LUKE MEISSNER"
    ],
    "secondary": [
      "TEXAS-KASYE BEVERS"
    ],
    "period": "FLOOR",
    "length": 110
  },
  "4": {
    "extras": [],
    "offense": "SHSU",
    "defense": "TEXAS",
    "time": "0300",
    "result": "GD",
    "primary": [
      "SHSU-CHRIS DORSEY"
    ],
    "secondary": [
      "SHSU-THOMAS MORGAN"
    ],
    "period": "FLOOR",
    "length": 80
  },
  "5": {
    "extras": [],
    "offense": "TEXAS",
    "defense": "SHSU",
    "time": "0317",
    "result": "GD",
    "primary": [
      "TEXAS-LUKE MEISSNER"
    ],
    "secondary": [],
    "period": "FLOOR",
    "length": 17
  },
  "6": {
    "extras": [],
    "offense": "SHSU",
    "defense": "TEXAS",
    "time": "0340",
    "result": "EP",
    "primary": [
      "SHSU-KEENAN NASH"
    ],
    "secondary": [
      "SHSU-HAYDEN BOYES"
    ],
    "period": "FLOOR",
    "length": 23
  },
  "7": {
    "extras": [],
    "offense": "TEXAS",
    "defense": "SHSU",
    "time": "0403",
    "result": "GD",
    "primary": [
      "TEXAS-JOSH JOHNSON"
    ],
    "secondary": [
      "TEXAS-GRAYSON BRIGGS"
    ],
    "period": "FLOOR",
    "length": 63
  },
  "8": {
    "extras": [],
    "offense": "SHSU",
    "defense": "TEXAS",
    "time": "0421",
    "result": "ED",
    "primary": [
      "SHSU-HALEY DUPRE"
    ],
    "secondary": [
      "SHSU-KEENAN NASH"
    ],
    "period": "FLOOR",
    "length": 18
  },
  "9": {
    "extras": [],
    "offense": "TEXAS",
    "defense": "SHSU",
    "time": "0447",
    "result": "TB",
    "primary": [
      "SHSU-BALDEMAR NUNEZ"
    ],
    "secondary": [
      "TEXAS-GRAYSON BRIGGS"
    ],
    "period": "FLOOR",
    "length": 26
  },
  "10": {
    "extras": [],
    "offense": "SHSU",
    "defense": "TEXAS",
    "time": "0505",
    "result": "EP",
    "primary": [
      "SHSU-HALEY DUPRE"
    ],
    "secondary": [
      "SHSU-KEENAN NASH"
    ],
    "period": "FLOOR",
    "length": 58
  },
  "11": {
    "extras": [],
    "offense": "TEXAS",
    "defense": "SHSU",
    "time": "0607",
    "result": "GS",
    "primary": [
      "TEXAS-KASYE BEVERS"
    ],
    "secondary": [
      "TEXAS-DAVIS ROE"
    ],
    "period": "FLOOR",
    "length": 102
  },
  "12": {
    "extras": [],
    "offense": "SHSU",
    "defense": "TEXAS",
    "time": "0630",
    "result": "TD",
    "primary": [
      "TEXAS-MICHAEL JOHNSTON"
    ],
    "secondary": [
      "SHSU-BRANDON KUBENA",
      "SHSU-HALEY DUPRE"
    ],
    "period": "FLOOR",
    "length": 23
  },
  "13": {
    "extras": [],
    "offense": "TEXAS",
    "defense": "SHSU",
    "time": "0720",
    "result": "EP",
    "primary": [
      "TEXAS-DAVIS ROE"
    ],
    "secondary": [
      "TEXAS-KASYE BEVERS"
    ],
    "period": "FLOOR",
    "length": 90
  },
  "14": {
    "extras": [],
    "offense": "SHSU",
    "defense": "TEXAS",
    "time": "0805",
    "result": "TL",
    "primary": [
      "TEXAS-MICHAEL JOHNSTON"
    ],
    "secondary": [
      "SHSU-HALEY DUPRE"
    ],
    "period": "FLOOR",
    "length": 85
  },
  "15": {
    "extras": [],
    "offense": "TEXAS",
    "defense": "SHSU",
    "time": "0827",
    "result": "EB",
    "primary": [
      "TEXAS-TATE KAY"
    ],
    "secondary": [],
    "period": "FLOOR",
    "length": 22
  },
  "16": {
    "extras": [],
    "offense": "SHSU",
    "defense": "TEXAS",
    "time": "0836",
    "result": "GS",
    "primary": [
      "SHSU-KEENAN NASH"
    ],
    "secondary": [
      "SHSU-BRANDON KUBENA"
    ],
    "period": "FLOOR",
    "length": 9
  },
  "17": {
    "extras": [],
    "offense": "TEXAS",
    "defense": "SHSU",
    "time": "0931",
    "result": "ED",
    "primary": [
      "TEXAS-GABE OLIVO"
    ],
    "secondary": [
      "TEXAS-DAVIS ROE"
    ],
    "period": "FLOOR",
    "length": 95
  },
  "18": {
    "extras": [],
    "offense": "SHSU",
    "defense": "TEXAS",
    "time": "1026",
    "result": "GP",
    "primary": [
      "SHSU-BRANDON KUBENA"
    ],
    "secondary": [
      "SHSU-KEENAN NASH"
    ],
    "period": "FLOOR",
    "length": 95
  },
  "19": {
    "extras": [],
    "offense": "TEXAS",
    "defense": "SHSU",
    "time": "1044",
    "result": "EM",
    "primary": [
      "TEXAS-DAVIS ROE"
    ],
    "secondary": [],
    "period": "FLOOR",
    "length": 18
  },
  "20": {
    "extras": [],
    "offense": "SHSU",
    "defense": "TEXAS",
    "time": "1118",
    "result": "TB",
    "primary": [
      "TEXAS-JACK WANG"
    ],
    "secondary": [
      "SHSU-11"
    ],
    "period": "FLOOR",
    "length": 74
  },
  "21": {
    "extras": [],
    "offense": "TEXAS",
    "defense": "SHSU",
    "time": "1133",
    "result": "EM",
    "primary": [
      "TEXAS-DAVIS ROE"
    ],
    "secondary": [],
    "period": "FLOOR",
    "length": 15
  },
  "22": {
    "extras": [],
    "offense": "SHSU",
    "defense": "TEXAS",
    "time": "1222",
    "result": "TD",
    "primary": [
      "TEXAS-MICHAEL JOHNSTON"
    ],
    "secondary": [
      "SHSU-42",
      "SHSU-11"
    ],
    "period": "FLOOR",
    "length": 89
  },
  "23": {
    "extras": [],
    "offense": "TEXAS",
    "defense": "SHSU",
    "time": "1300",
    "result": "TD",
    "primary": [
      "SHSU-HAYDEN BOYES"
    ],
    "secondary": [
      "TEXAS-JOHN ANDERSON",
      "TEXAS-COLE BURKE"
    ],
    "period": "FLOOR",
    "length": 78
  },
  "24": {
    "extras": [],
    "offense": "SHSU",
    "defense": "TEXAS",
    "time": "1322",
    "result": "TB",
    "primary": [
      "TEXAS-SAM SELLE"
    ],
    "secondary": [
      "SHSU-11"
    ],
    "period": "FLOOR",
    "length": 22
  },
  "25": {
    "extras": [],
    "offense": "TEXAS",
    "defense": "SHSU",
    "time": "1338",
    "result": "TD",
    "primary": [
      "SHSU-BRANDON KUBENA"
    ],
    "secondary": [
      "TEXAS-KASYE BEVERS",
      "TEXAS-CAROLINE TAO"
    ],
    "period": "FLOOR",
    "length": 16
  },
  "26": {
    "extras": [],
    "offense": "SHSU",
    "defense": "TEXAS",
    "time": "1422",
    "result": "GS",
    "primary": [
      "SHSU-THOMAS MORGAN"
    ],
    "secondary": [
      "SHSU-CHRIS DORSEY"
    ],
    "period": "FLOOR",
    "length": 84
  },
  "27": {
    "extras": [],
    "offense": "TEXAS",
    "defense": "SHSU",
    "time": "1438",
    "result": "GP",
    "primary": [
      "TEXAS-COLE BURKE"
    ],
    "secondary": [
      "TEXAS-JOHN ANDERSON"
    ],
    "period": "FLOOR",
    "length": 16
  },
  "28": {
    "extras": [],
    "offense": "SHSU",
    "defense": "TEXAS",
    "time": "1522",
    "result": "EM",
    "primary": [
      "SHSU-HAYDEN BOYES"
    ],
    "secondary": [],
    "period": "FLOOR",
    "length": 84
  },
  "29": {
    "extras": [],
    "offense": "TEXAS",
    "defense": "SHSU",
    "time": "1537",
    "result": "GD",
    "primary": [
      "TEXAS-JOHN ANDERSON"
    ],
    "secondary": [],
    "period": "FLOOR",
    "length": 15
  },
  "30": {
    "extras": [],
    "offense": "SHSU",
    "defense": "TEXAS",
    "time": "1621",
    "result": "ED",
    "primary": [
      "SHSU-HALEY DUPRE"
    ],
    "secondary": [
      "SHSU-KEENAN NASH"
    ],
    "period": "FLOOR",
    "length": 84
  },
  "31": {
    "extras": [],
    "offense": "TEXAS",
    "defense": "SHSU",
    "time": "1640",
    "result": "GP",
    "primary": [
      "TEXAS-COLE BURKE"
    ],
    "secondary": [
      "TEXAS-JOHN ANDERSON"
    ],
    "period": "FLOOR",
    "length": 19
  },
  "32": {
    "extras": [],
    "offense": "SHSU",
    "defense": "TEXAS",
    "time": "1823",
    "result": "TL",
    "primary": [
      "TEXAS-COLE BURKE"
    ],
    "secondary": [
      "SHSU-42"
    ],
    "period": "SOP",
    "length": 183
  },
  "33": {
    "extras": [],
    "offense": "TEXAS",
    "defense": "SHSU",
    "time": "1837",
    "result": "GD",
    "primary": [
      "TEXAS-JOSH JOHNSON"
    ],
    "secondary": [],
    "period": "SOP",
    "length": 14
  },
  "34": {
    "extras": [],
    "offense": "SHSU",
    "defense": "TEXAS",
    "time": "1919",
    "result": "TB",
    "primary": [
      "TEXAS-TATE KAY"
    ],
    "secondary": [
      "SHSU-BRANDON KUBENA"
    ],
    "period": "SOP",
    "length": 82
  },
  "35": {
    "extras": [],
    "offense": "TEXAS",
    "defense": "SHSU",
    "time": "1933",
    "result": "GP",
    "primary": [
      "TEXAS-KASYE BEVERS"
    ],
    "secondary": [
      "TEXAS-LUKE MEISSNER"
    ],
    "period": "SOP",
    "length": 14
  },
  "36": {
    "extras": [],
    "offense": "SHSU",
    "defense": "TEXAS",
    "time": "2003",
    "result": "EM",
    "primary": [
      "SHSU-BRANDON KUBENA"
    ],
    "secondary": [],
    "period": "SOP",
    "length": 70
  },
  "37": {
    "extras": [],
    "offense": "TEXAS",
    "defense": "SHSU",
    "time": "2018",
    "result": "GD",
    "primary": [
      "TEXAS-JOSH JOHNSON"
    ],
    "secondary": [],
    "period": "SOP",
    "length": 15
  },
  "38": {
    "extras": [],
    "offense": "SHSU",
    "defense": "TEXAS",
    "time": "2058",
    "result": "TD",
    "primary": [
      "TEXAS-LUKE MEISSNER"
    ],
    "secondary": [
      "SHSU-77",
      "SHSU-HALEY DUPRE"
    ],
    "period": "SOP",
    "length": 40
  },
  "39": {
    "extras": [],
    "offense": "TEXAS",
    "defense": "SHSU",
    "time": "2121",
    "result": "GP",
    "primary": [
      "TEXAS-CAROLINE TAO"
    ],
    "secondary": [
      "TEXAS-JOSH JOHNSON"
    ],
    "period": "SOP",
    "length": 63
  },
  "40": {
    "extras": [],
    "offense": "SHSU",
    "defense": "TEXAS",
    "time": "2205",
    "result": "ED",
    "primary": [
      "SHSU-25"
    ],
    "secondary": [],
    "period": "SOP",
    "length": 84
  },
  "41": {
    "extras": [],
    "offense": "TEXAS",
    "defense": "SHSU",
    "time": "2208",
    "result": "GS",
    "primary": [
      "TEXAS-JOSH JOHNSON"
    ],
    "secondary": [],
    "period": "SOP",
    "length": 3
  },
  "42": {
    "extras": [],
    "offense": "SHSU",
    "defense": "TEXAS",
    "time": "2253",
    "result": "EP",
    "primary": [
      "SHSU-KEENAN NASH"
    ],
    "secondary": [
      "SHSU-21"
    ],
    "period": "SOP",
    "length": 45
  },
  "43": {
    "extras": [],
    "offense": "TEXAS",
    "defense": "SHSU",
    "time": "2259",
    "result": "RCA",
    "primary": [
      "TEXAS-JOHN ANDERSON"
    ],
    "secondary": [],
    "period": "SOP",
    "length": -1
  }
}