{
  "0": {
    "defense": "",
    "offense": "Brooms Up",
    "result": "BU",
    "time": "0000",
    "length": -1,
    "extras": [],
    "primary": [
      "TEXAS-DAVIS ROE"
    ],
    "period": "FLOOR",
    "secondary": [
      "KANSAS-23"
    ]
  },
  "1": {
    "defense": "KANSAS",
    "offense": "TEXAS",
    "result": "GS",
    "time": "",
    "extras": [],
    "length": -1,
    "primary": [
      "TEXAS-LUKE MEISSNER"
    ],
    "period": "FLOOR",
    "secondary": []
  },
  "2": {
    "defense": "TEXAS",
    "offense": "KANSAS",
    "result": "TD",
    "time": "",
    "extras": [],
    "length": -1,
    "primary": [
      "TEXAS-AIDAN PARSI"
    ],
    "period": "FLOOR",
    "secondary": [
      "KANSAS-UNK"
    ]
  },
  "3": {
    "defense": "KANSAS",
    "offense": "TEXAS",
    "result": "GD",
    "time": "",
    "extras": [],
    "length": -1,
    "primary": [
      "TEXAS-AIDAN PARSI"
    ],
    "period": "FLOOR",
    "secondary": []
  },
  "4": {
    "defense": "TEXAS",
    "offense": "KANSAS",
    "result": "ED",
    "time": "",
    "extras": [],
    "length": -1,
    "primary": [
      "KANSAS-UNK"
    ],
    "period": "FLOOR",
    "secondary": []
  },
  "5": {
    "defense": "KANSAS",
    "offense": "TEXAS",
    "result": "GD",
    "time": "",
    "extras": [],
    "length": -1,
    "primary": [
      "TEXAS-DAVIS ROE"
    ],
    "period": "FLOOR",
    "secondary": []
  },
  "6": {
    "defense": "TEXAS",
    "offense": "KANSAS",
    "result": "GP",
    "time": "",
    "extras": [],
    "length": -1,
    "primary": [
      "KANSAS-UNK"
    ],
    "period": "FLOOR",
    "secondary": [
      "KANSAS-UNK"
    ]
  },
  "7": {
    "defense": "KANSAS",
    "offense": "TEXAS",
    "result": "ED",
    "time": "",
    "extras": [],
    "length": -1,
    "primary": [
      "TEXAS-LUKE MEISSNER"
    ],
    "period": "FLOOR",
    "secondary": []
  },
  "8": {
    "defense": "TEXAS",
    "offense": "KANSAS",
    "result": "GP",
    "time": "",
    "extras": [],
    "length": -1,
    "primary": [
      "KANSAS-UNK"
    ],
    "period": "FLOOR",
    "secondary": [
      "KANSAS-RACHEL HEALD"
    ]
  },
  "9": {
    "defense": "KANSAS",
    "offense": "TEXAS",
    "result": "EM",
    "time": "",
    "extras": [],
    "length": -1,
    "primary": [
      "TEXAS-DAVIS ROE"
    ],
    "period": "FLOOR",
    "secondary": []
  },
  "10": {
    "defense": "TEXAS",
    "offense": "KANSAS",
    "result": "EM",
    "time": "",
    "extras": [],
    "length": -1,
    "primary": [
      "KANSAS-BRANDON TABOR"
    ],
    "period": "FLOOR",
    "secondary": []
  },
  "11": {
    "defense": "KANSAS",
    "offense": "TEXAS",
    "result": "EP",
    "time": "",
    "extras": [],
    "length": -1,
    "primary": [
      "TEXAS-UNK"
    ],
    "period": "FLOOR",
    "secondary": [
      "TEXAS-KASYE BEVERS"
    ]
  },
  "12": {
    "defense": "TEXAS",
    "offense": "KANSAS",
    "result": "TB",
    "time": "",
    "extras": [],
    "length": -1,
    "primary": [
      "TEXAS-JACK WANG"
    ],
    "period": "FLOOR",
    "secondary": [
      "KANSAS-85"
    ]
  },
  "13": {
    "defense": "KANSAS",
    "offense": "TEXAS",
    "result": "GD",
    "time": "",
    "extras": [
      [
        "Y",
        "KANSAS-BEN ENGELS"
      ]
    ],
    "length": -1,
    "primary": [
      "TEXAS-DAVIS ROE"
    ],
    "period": "FLOOR",
    "secondary": [
      "TEXAS-JOSH JOHNSON"
    ]
  },
  "14": {
    "defense": "TEXAS",
    "offense": "KANSAS",
    "result": "EP",
    "time": "",
    "extras": [],
    "length": -1,
    "primary": [
      "KANSAS-85"
    ],
    "period": "FLOOR",
    "secondary": [
      "KANSAS-RACHEL HEALD"
    ]
  },
  "15": {
    "defense": "KANSAS",
    "offense": "TEXAS",
    "result": "EM",
    "time": "",
    "extras": [],
    "length": -1,
    "primary": [
      "TEXAS-JOSH JOHNSON"
    ],
    "period": "FLOOR",
    "secondary": []
  },
  "16": {
    "defense": "TEXAS",
    "offense": "KANSAS",
    "result": "EP",
    "time": "",
    "extras": [],
    "length": -1,
    "primary": [
      "KANSAS-RACHEL HEALD"
    ],
    "period": "FLOOR",
    "secondary": [
      "KANSAS-BEN ENGELS"
    ]
  },
  "17": {
    "defense": "KANSAS",
    "offense": "TEXAS",
    "result": "GP",
    "time": "",
    "extras": [],
    "length": -1,
    "primary": [
      "TEXAS-KASYE BEVERS"
    ],
    "period": "FLOOR",
    "secondary": [
      "TEXAS-LUKE MEISSNER"
    ]
  },
  "18": {
    "defense": "TEXAS",
    "offense": "KANSAS",
    "result": "TD",
    "time": "",
    "extras": [],
    "length": -1,
    "primary": [
      "TEXAS-DYLAN BOTTOMS"
    ],
    "period": "FLOOR",
    "secondary": [
      "KANSAS-RACHEL HEALD",
      "KANSAS-85"
    ]
  },
  "19": {
    "defense": "KANSAS",
    "offense": "TEXAS",
    "result": "TD",
    "time": "",
    "extras": [],
    "length": -1,
    "primary": [
      "KANSAS-RACHEL HEALD"
    ],
    "period": "FLOOR",
    "secondary": [
      "TEXAS-JOSH JOHNSON",
      "TEXAS-KASYE BEVERS"
    ]
  },
  "20": {
    "defense": "TEXAS",
    "offense": "KANSAS",
    "result": "GS",
    "time": "",
    "extras": [],
    "length": -1,
    "primary": [
      "KANSAS-85"
    ],
    "period": "FLOOR",
    "secondary": []
  },
  "21": {
    "defense": "KANSAS",
    "offense": "TEXAS",
    "result": "GD",
    "time": "",
    "extras": [],
    "length": -1,
    "primary": [
      "TEXAS-LUKE MEISSNER"
    ],
    "period": "FLOOR",
    "secondary": [
      "TEXAS-AIDAN PARSI"
    ]
  },
  "22": {
    "defense": "TEXAS",
    "offense": "KANSAS",
    "result": "TC",
    "time": "",
    "extras": [],
    "length": -1,
    "primary": [
      "TEXAS-AIDAN PARSI"
    ],
    "period": "FLOOR",
    "secondary": [
      "KANSAS-BRANDON TABOR"
    ]
  },
  "23": {
    "defense": "KANSAS",
    "offense": "TEXAS",
    "result": "EY",
    "time": "",
    "extras": [],
    "length": -1,
    "primary": [
      "TEXAS-JACK WANG"
    ],
    "period": "FLOOR",
    "secondary": []
  },
  "24": {
    "defense": "TEXAS",
    "offense": "KANSAS",
    "result": "ED",
    "time": "",
    "extras": [],
    "length": -1,
    "primary": [
      "KANSAS-RYAN DICKEY"
    ],
    "period": "FLOOR",
    "secondary": []
  },
  "25": {
    "defense": "KANSAS",
    "offense": "TEXAS",
    "result": "EM",
    "time": "",
    "extras": [],
    "length": -1,
    "primary": [
      "TEXAS-AIDAN PARSI"
    ],
    "period": "FLOOR",
    "secondary": []
  },
  "26": {
    "defense": "TEXAS",
    "offense": "KANSAS",
    "result": "GS",
    "time": "",
    "extras": [
      [
        "Y",
        "TEXAS-AIDAN PARSI"
      ]
    ],
    "length": -1,
    "primary": [
      "KANSAS-15"
    ],
    "period": "FLOOR",
    "secondary": [
      "KANSAS-BRANDON TABOR"
    ]
  },
  "27": {
    "defense": "KANSAS",
    "offense": "TEXAS",
    "result": "TC",
    "time": "",
    "extras": [],
    "length": -1,
    "primary": [
      "KANSAS-15"
    ],
    "period": "FLOOR",
    "secondary": [
      "TEXAS-GRAYSON BRIGGS"
    ]
  },
  "28": {
    "defense": "TEXAS",
    "offense": "KANSAS",
    "result": "TD",
    "time": "",
    "extras": [],
    "length": -1,
    "primary": [
      "TEXAS-DAVIS ROE"
    ],
    "period": "FLOOR",
    "secondary": [
      "KANSAS-RACHEL HEALD",
      "KANSAS-15"
    ]
  },
  "29": {
    "defense": "KANSAS",
    "offense": "TEXAS",
    "result": "ET",
    "time": "",
    "extras": [],
    "length": -1,
    "primary": [
      "TEXAS-RICHMOND KEELING"
    ],
    "period": "FLOOR",
    "secondary": []
  },
  "30": {
    "defense": "TEXAS",
    "offense": "KANSAS",
    "result": "ED",
    "time": "",
    "extras": [],
    "length": -1,
    "primary": [
      "KANSAS-BEN ENGELS"
    ],
    "period": "FLOOR",
    "secondary": [
      "KANSAS-85"
    ]
  },
  "31": {
    "defense": "KANSAS",
    "offense": "TEXAS",
    "result": "GD",
    "time": "",
    "extras": [],
    "length": -1,
    "primary": [
      "TEXAS-GRAYSON BRIGGS"
    ],
    "period": "FLOOR",
    "secondary": []
  },
  "32": {
    "defense": "TEXAS",
    "offense": "KANSAS",
    "result": "TB",
    "time": "",
    "extras": [],
    "length": -1,
    "primary": [
      "TEXAS-KYLIE MCBRIDE"
    ],
    "period": "FLOOR",
    "secondary": [
      "KANSAS-85"
    ]
  },
  "33": {
    "defense": "KANSAS",
    "offense": "TEXAS",
    "result": "GD",
    "time": "",
    "extras": [],
    "length": -1,
    "primary": [
      "TEXAS-LUKE MEISSNER"
    ],
    "period": "FLOOR",
    "secondary": []
  },
  "34": {
    "defense": "TEXAS",
    "offense": "KANSAS",
    "result": "EP",
    "time": "",
    "extras": [],
    "length": -1,
    "primary": [
      "KANSAS-BEN ENGELS"
    ],
    "period": "FLOOR",
    "secondary": []
  },
  "35": {
    "defense": "KANSAS",
    "offense": "TEXAS",
    "result": "GD",
    "time": "",
    "extras": [],
    "length": -1,
    "primary": [
      "TEXAS-AIDAN PARSI"
    ],
    "period": "FLOOR",
    "secondary": []
  },
  "36": {
    "defense": "TEXAS",
    "offense": "KANSAS",
    "result": "TB",
    "time": "",
    "extras": [],
    "length": -1,
    "primary": [
      "TEXAS-JACK WANG"
    ],
    "period": "FLOOR",
    "secondary": [
      "KANSAS-BRANDON TABOR"
    ]
  },
  "37": {
    "defense": "KANSAS",
    "offense": "TEXAS",
    "result": "GD",
    "time": "",
    "extras": [
      [
        "Y",
        "KANSAS-MIKE DEVINE"
      ]
    ],
    "length": -1,
    "primary": [
      "TEXAS-AIDAN PARSI"
    ],
    "period": "FLOOR",
    "secondary": []
  },
  "38": {
    "defense": "TEXAS",
    "offense": "KANSAS",
    "result": "EP",
    "time": "",
    "extras": [],
    "length": -1,
    "primary": [
      "KANSAS-BRANDON TABOR"
    ],
    "period": "FLOOR",
    "secondary": [
      "KANSAS-17"
    ]
  },
  "39": {
    "defense": "KANSAS",
    "offense": "TEXAS",
    "result": "TC",
    "time": "",
    "extras": [],
    "length": -1,
    "primary": [
      "KANSAS-IAN MCCABE"
    ],
    "period": "FLOOR",
    "secondary": [
      "TEXAS-LUKE MEISSNER"
    ]
  },
  "40": {
    "defense": "TEXAS",
    "offense": "KANSAS",
    "result": "TB",
    "time": "",
    "extras": [],
    "length": -1,
    "primary": [
      "TEXAS-TATE KAY"
    ],
    "period": "FLOOR",
    "secondary": [
      "KANSAS-BRANDON TABOR"
    ]
  },
  "41": {
    "defense": "KANSAS",
    "offense": "TEXAS",
    "result": "GP",
    "time": "",
    "extras": [],
    "length": -1,
    "primary": [
      "TEXAS-KASYE BEVERS"
    ],
    "period": "FLOOR",
    "secondary": [
      "TEXAS-LUKE MEISSNER"
    ]
  },
  "42": {
    "defense": "TEXAS",
    "offense": "KANSAS",
    "result": "RCA",
    "time": "",
    "extras": [],
    "length": -1,
    "primary": [
      "TEXAS-JOEY CASTELLANO"
    ],
    "period": "FLOOR",
    "secondary": []
  }
}